<?xml version="1.0" encoding="utf-8"?>
<!DOCTYPE hibernate-mapping PUBLIC "-//Hibernate/Hibernate Mapping DTD 3.0//EN"
"http://hibernate.sourceforge.net/hibernate-mapping-3.0.dtd">
	<!--
		Mapping file autogenerated by MyEclipse Persistence Tools
	-->
<hibernate-mapping>
	<class name="cn.ss.entity.SoftwareInfo" table="softwareInfo"
		catalog="softwarestation">
		<id name="id" type="java.lang.Integer">
			<column name="id" />
			<generator class="native" />
		</id>
		<property name="name" type="java.lang.String">
			<column name="name" length="20">
				<comment>名称</comment>
			</column>
		</property>
		<many-to-one name="softwareType">
			<column name="type">
				<comment>分类</comment>
			</column>
		</many-to-one>
		<property name="description" type="java.lang.String">
			<column name="description" length="2000">
				<comment>简介/描述</comment>
			</column>
		</property>
		<property name="imgPath" type="java.lang.String">
			<column name="imgPath" length="200">
				<comment>截图地址</comment>
			</column>
		</property>
		<property name="click" type="java.lang.Integer">
			<column name="click">
				<comment>点击数</comment>
			</column>
		</property>

		<property name="download" type="java.lang.Integer">
			<column name="download">
				<comment>下载</comment>
			</column>
		</property>
		<property name="active" type="java.lang.Integer">
			<column name="active">
				<comment>激活</comment>
			</column>
		</property>
		<property name="allPrice" type="java.lang.Double">
			<column name="allprice">
				<comment>总金额</comment>
			</column>
		</property>
		<property name="producer" type="java.lang.String">
			<column name="producer" length="200">
				<comment>软件开发商</comment>
			</column>
		</property>

		<property name="safety" type="java.lang.String">
			<column name="safety" length="20">
				<comment>安全</comment>
			</column>
		</property>
		<property name="traffic" type="java.lang.Double">
			<column name="traffic" precision="22" scale="0">
				<comment>资费</comment>
			</column>
		</property>
		<property name="createTime" type="java.util.Date">
			<column name="createTime" length="19">
				<comment>更新时间</comment>
			</column>
		</property>
		<property name="prompt" type="java.lang.String">
			<column name="prompt" length="200">
				<comment>提示</comment>
			</column>
		</property>
		<property name="recommend" type="java.lang.Integer">
			<column name="recommend">
				<comment>是否推荐0.否，1.是</comment>
			</column>
		</property>
		<property name="isShow" type="java.lang.Integer">
			<column name="isShow">
				<comment>是否显示0.否，1.是</comment>
			</column>
		</property>
		<property name="plusFine" type="java.lang.Integer">
			<column name="plusFine">
				<comment>是否加精0.否，1.是</comment>
			</column>
		</property>
		<property name="promotionWay" type="java.lang.Integer">
			<column name="promotionWay">
				<comment>推广方式0.提成，1.免费</comment>
			</column>
		</property>

		<property name="number" type="java.lang.Integer">
			<column name="number">
				<comment>软件数量</comment>
			</column>
		</property>

		<property name="isRename" type="java.lang.Integer">
			<column name="isRename">
				<comment>上传文件是否允许改名</comment>
			</column>
		</property>
		<bag name="softwareList" cascade="all">
			<key>
				<column name="softwareInfoId">
					<comment>软件</comment>
				</column>
			</key>
			<one-to-many class="cn.ss.entity.Software" />
		</bag>
		<bag name="activeLogList" cascade="all">
			<key>
				<column name="softwareId">
					<comment>激活日志</comment>
				</column>
			</key>
			<one-to-many class="cn.ss.entity.ActiveLog" />
		</bag>
		<bag name="clickLogList" cascade="all">
			<key>
				<column name="softwareId">
					<comment>点击日志</comment>
				</column>
			</key>
			<one-to-many class="cn.ss.entity.ClickLog" />
		</bag>
		<bag name="downloadLogList" cascade="all">
			<key>
				<column name="softwareId">
					<comment>下载日志</comment>
				</column>
			</key>
			<one-to-many class="cn.ss.entity.DownloadLog" />
		</bag>
	</class>
</hibernate-mapping>
